lyriks/__init__.py
lyriks/const.py
lyriks/logging.py
lyriks/lyrics_fetcher.py
lyriks/mb_client.py
lyriks/cli/__init__.py
lyriks/cli/console.py
lyriks/cli/default_group.py
lyriks/cli/provider_choice.py
lyriks/cli/url_param_type.py
lyriks/lib/zzc_sign.py
lyriks/lyrics/__init__.py
lyriks/lyrics/lyrics.py
lyriks/lyrics/util.py
lyriks/providers/__init__.py
lyriks/providers/genie.py
lyriks/providers/provider.py
lyriks/providers/qqm.py
lyriks/providers/registry.py
lyriks/providers/util.py
lyriks/providers/vibe.py
lyriks/providers/api/genie_api.py
lyriks/providers/api/qqm_api.py
lyriks/providers/api/song.py
lyriks/providers/api/vibe_api.py
lyriks-0.5.7.dist-info/licenses/LICENSE
lyriks-0.5.7.dist-info/METADATA
lyriks-0.5.7.dist-info/WHEEL
lyriks-0.5.7.dist-info/entry_points.txt
lyriks-0.5.7.dist-info/top_level.txt
lyriks-0.5.7.dist-info/RECORD
