Metadata-Version: 2.4
Name: lyriks
Version: 0.5.7
Summary: A command line tool to fetch lyrics from Genie
Author-email: Maxr1998 <max@maxr1998.de>
License-Expression: GPL-3.0-or-later
Classifier: Programming Language :: Python :: 3
Classifier: Operating System :: OS Independent
Requires-Python: >=3.10
License-File: LICENSE
Requires-Dist: click>=8.0.0
Requires-Dist: httpx[http2]>=0.22.0
Requires-Dist: lxml>=4.8.0
Requires-Dist: mutagen>=1.45
Requires-Dist: pyqqmusicdes>=0.1.0
Requires-Dist: rich>=11.2.0
Requires-Dist: stamina>=25.2.0
Requires-Dist: trio>=0.19.0
Dynamic: license-file
